grap/core/__init__.py
grap/core/action.py
grap/core/common.py
grap/core/errors.py
grap/core/parser.py
grap/core/rules.py
grap-0.1.0b1.dist-info/LICENSE
grap-0.1.0b1.dist-info/METADATA
grap-0.1.0b1.dist-info/WHEEL
grap-0.1.0b1.dist-info/top_level.txt
grap-0.1.0b1.dist-info/RECORD
